pproxy/__doc__.py
pproxy/__init__.py
pproxy/__main__.py
pproxy/cipher.py
pproxy/cipherpy.py
pproxy/plugin.py
pproxy/proto.py
pproxy/server.py
pproxy/sysproxy.py
pproxy/verbose.py
pproxy_ext-2.7.9.dist-info/LICENSE
pproxy_ext-2.7.9.dist-info/METADATA
pproxy_ext-2.7.9.dist-info/WHEEL
pproxy_ext-2.7.9.dist-info/entry_points.txt
pproxy_ext-2.7.9.dist-info/top_level.txt
pproxy_ext-2.7.9.dist-info/RECORD
